sparseml/__init__.py
sparseml/analytics.py
sparseml/base.py
sparseml/integration_helper_functions.py
sparseml/log.py
sparseml/version.py
sparseml/benchmark/__init__.py
sparseml/benchmark/info.py
sparseml/benchmark/serialization.py
sparseml/core/__init__.py
sparseml/core/event.py
sparseml/core/factory.py
sparseml/core/framework.py
sparseml/core/framework_object.py
sparseml/core/helpers.py
sparseml/core/session.py
sparseml/core/state.py
sparseml/core/data/__init__.py
sparseml/core/data/base.py
sparseml/core/data/pytorch.py
sparseml/core/lifecycle/__init__.py
sparseml/core/lifecycle/event.py
sparseml/core/lifecycle/session.py
sparseml/core/logger/__init__.py
sparseml/core/logger/logger.py
sparseml/core/logger/utils/__init__.py
sparseml/core/logger/utils/frequency_manager.py
sparseml/core/model/__init__.py
sparseml/core/model/base.py
sparseml/core/model/pytorch.py
sparseml/core/modifier/__init__.py
sparseml/core/modifier/base.py
sparseml/core/modifier/modifier.py
sparseml/core/modifier/stage.py
sparseml/core/optimizer/__init__.py
sparseml/core/optimizer/base.py
sparseml/core/optimizer/pytorch.py
sparseml/core/recipe/__init__.py
sparseml/core/recipe/args.py
sparseml/core/recipe/base.py
sparseml/core/recipe/container.py
sparseml/core/recipe/metadata.py
sparseml/core/recipe/modifier.py
sparseml/core/recipe/recipe.py
sparseml/core/recipe/stage.py
sparseml/deepsparse/__init__.py
sparseml/deepsparse/base.py
sparseml/deepsparse/framework/__init__.py
sparseml/deepsparse/framework/info.py
sparseml/deepsparse/sparsification/__init__.py
sparseml/deepsparse/sparsification/info.py
sparseml/evaluation/__init__.py
sparseml/evaluation/cli.py
sparseml/evaluation/evaluator.py
sparseml/evaluation/integrations_config.yaml
sparseml/evaluation/registry.py
sparseml/evaluation/integrations/__init__.py
sparseml/evaluation/integrations/lm_evaluation_harness.py
sparseml/evaluation/integrations/perplexity.py
sparseml/export/__init__.py
sparseml/export/export.py
sparseml/export/export_data.py
sparseml_nightly-1.8.0.20240630.dist-info/LICENSE
sparseml_nightly-1.8.0.20240630.dist-info/LICENSE-ULTRALYTICS
sparseml_nightly-1.8.0.20240630.dist-info/METADATA
sparseml_nightly-1.8.0.20240630.dist-info/NOTICE
sparseml_nightly-1.8.0.20240630.dist-info/WHEEL
sparseml_nightly-1.8.0.20240630.dist-info/entry_points.txt
sparseml_nightly-1.8.0.20240630.dist-info/top_level.txt
sparseml_nightly-1.8.0.20240630.dist-info/RECORD
