Metadata-Version: 2.1
Name: sparseml-nightly
Version: 1.8.0.20240630
Summary: Libraries for applying sparsification recipes to neural networks with a few lines of code, enabling faster and smaller models
Home-page: https://github.com/neuralmagic/sparseml
Author: Neuralmagic, Inc.
Author-email: support@neuralmagic.com
License: Apache
Keywords: inference,machine learning,neural network,computer vision,nlp,cv,deep learning,torch,pytorch,tensorflow,keras,sparsity,pruning,deep learning libraries,onnx,quantization,automl
Classifier: Development Status :: 5 - Production/Stable
Classifier: Programming Language :: Python :: 3
Classifier: Programming Language :: Python :: 3 :: Only
Classifier: Intended Audience :: Developers
Classifier: Intended Audience :: Education
Classifier: Intended Audience :: Information Technology
Classifier: Intended Audience :: Science/Research
Classifier: License :: OSI Approved :: Apache Software License
Classifier: Operating System :: POSIX :: Linux
Classifier: Topic :: Scientific/Engineering
Classifier: Topic :: Scientific/Engineering :: Artificial Intelligence
Classifier: Topic :: Scientific/Engineering :: Mathematics
Classifier: Topic :: Software Development
Classifier: Topic :: Software Development :: Libraries :: Python Modules
Requires-Python: >=3.8.0,<3.12
License-File: LICENSE
License-File: LICENSE-ULTRALYTICS
License-File: NOTICE
Requires-Dist: sparsezoo-nightly >=1.7.0
Requires-Dist: pyyaml >=5.0.0
Requires-Dist: numpy <2.0,>=1.17.0
Requires-Dist: matplotlib >=3.0.0
Requires-Dist: merge-args >=0.1.0
Requires-Dist: onnx <1.15.0,>=1.5.0
Requires-Dist: pandas >=0.25.0
Requires-Dist: packaging >=20.0
Requires-Dist: psutil >=5.0.0
Requires-Dist: pydantic <2.8.0,>=2.0.0
Requires-Dist: requests >=2.0.0
Requires-Dist: scikit-learn >=0.24.2
Requires-Dist: tqdm >=4.0.0
Requires-Dist: toposort >=1.0
Requires-Dist: GPUtil >=1.4.0
Requires-Dist: protobuf <=3.20.3,>=3.12.2
Requires-Dist: click !=8.0.0,>=7.1.2
Requires-Dist: scipy <1.9.2,>=1.8 ; python_version <= "3.9"
Requires-Dist: scipy >=1.0.0 ; python_version > "3.9"
Provides-Extra: clip
Requires-Dist: open-clip-torch ==2.20.0 ; extra == 'clip'
Provides-Extra: deepsparse
Requires-Dist: deepsparse-nightly >=1.7.0 ; extra == 'deepsparse'
Provides-Extra: deepsparse-ent
Requires-Dist: deepsparse-ent >=1.7.0 ; extra == 'deepsparse-ent'
Provides-Extra: dev
Requires-Dist: beautifulsoup4 ==4.9.3 ; extra == 'dev'
Requires-Dist: black ==22.12.0 ; extra == 'dev'
Requires-Dist: flake8 ==3.9.2 ; extra == 'dev'
Requires-Dist: isort ==5.8.0 ; extra == 'dev'
Requires-Dist: wheel >=0.36.2 ; extra == 'dev'
Requires-Dist: pytest >=6.0.0 ; extra == 'dev'
Requires-Dist: pytest-mock >=3.6.0 ; extra == 'dev'
Requires-Dist: pytest-rerunfailures >=13.0 ; extra == 'dev'
Requires-Dist: tensorboard <2.9,>=1.0 ; extra == 'dev'
Requires-Dist: tensorboardX >=1.0 ; extra == 'dev'
Requires-Dist: evaluate >=0.4.1 ; extra == 'dev'
Requires-Dist: parameterized ; extra == 'dev'
Provides-Extra: docs
Requires-Dist: m2r2 >=0.2.7 ; extra == 'docs'
Requires-Dist: mistune <3,>=2.0.3 ; extra == 'docs'
Requires-Dist: myst-parser >=0.14.0 ; extra == 'docs'
Requires-Dist: rinohtype ~=0.4.2 ; extra == 'docs'
Requires-Dist: sphinx ~=3.5.0 ; extra == 'docs'
Requires-Dist: sphinx-copybutton ~=0.3.0 ; extra == 'docs'
Requires-Dist: sphinx-markdown-tables ~=0.0.15 ; extra == 'docs'
Requires-Dist: sphinx-multiversion ~=0.2.4 ; extra == 'docs'
Requires-Dist: sphinx-pydantic ~=0.1.0 ; extra == 'docs'
Requires-Dist: sphinx-rtd-theme ~=0.5.0 ; extra == 'docs'
Requires-Dist: docutils <0.17 ; extra == 'docs'
Provides-Extra: llm
Requires-Dist: torch >=1.7.0 ; extra == 'llm'
Requires-Dist: gputils ; extra == 'llm'
Requires-Dist: transformers <4.41 ; extra == 'llm'
Requires-Dist: datasets <2.19 ; extra == 'llm'
Requires-Dist: dvc ; extra == 'llm'
Requires-Dist: scikit-learn ; extra == 'llm'
Requires-Dist: seqeval ; extra == 'llm'
Requires-Dist: einops ; extra == 'llm'
Requires-Dist: evaluate >=0.4.1 ; extra == 'llm'
Requires-Dist: accelerate >=0.20.3 ; extra == 'llm'
Requires-Dist: safetensors >=0.4.1 ; extra == 'llm'
Requires-Dist: compressed-tensors-nightly ; extra == 'llm'
Requires-Dist: sentencepiece ; extra == 'llm'
Provides-Extra: notebook
Requires-Dist: jupyter >=1.0.0 ; extra == 'notebook'
Requires-Dist: ipywidgets >=7.0.0 ; extra == 'notebook'
Provides-Extra: onnxruntime
Requires-Dist: onnxruntime >=1.0.0 ; extra == 'onnxruntime'
Provides-Extra: openpifpaf
Requires-Dist: openpifpaf ==0.13.6 ; extra == 'openpifpaf'
Provides-Extra: tf_keras
Requires-Dist: tensorflow ~=2.2.0 ; extra == 'tf_keras'
Requires-Dist: keras2onnx >=1.0.0 ; extra == 'tf_keras'
Provides-Extra: tf_v1
Requires-Dist: tensorflow <2.0.0 ; extra == 'tf_v1'
Requires-Dist: tensorboard <2.0.0 ; extra == 'tf_v1'
Requires-Dist: tf2onnx <1.6,>=1.0.0 ; extra == 'tf_v1'
Provides-Extra: tf_v1_gpu
Requires-Dist: tensorflow-gpu <2.0.0 ; extra == 'tf_v1_gpu'
Requires-Dist: tensorboard <2.0.0 ; extra == 'tf_v1_gpu'
Requires-Dist: tf2onnx <1.6,>=1.0.0 ; extra == 'tf_v1_gpu'
Provides-Extra: torch
Requires-Dist: torch >=1.7.0 ; extra == 'torch'
Requires-Dist: gputils ; extra == 'torch'
Provides-Extra: torch_all
Requires-Dist: torch >=1.7.0 ; extra == 'torch_all'
Requires-Dist: gputils ; extra == 'torch_all'
Requires-Dist: torchvision <0.17,>=0.3.0 ; extra == 'torch_all'
Requires-Dist: torchaudio <=2.0.1 ; extra == 'torch_all'
Provides-Extra: torchvision
Requires-Dist: torch >=1.7.0 ; extra == 'torchvision'
Requires-Dist: gputils ; extra == 'torchvision'
Requires-Dist: torchvision <0.17,>=0.3.0 ; extra == 'torchvision'
Requires-Dist: opencv-python <=4.6.0.66 ; extra == 'torchvision'
Provides-Extra: transformers
Requires-Dist: torch >=1.7.0 ; extra == 'transformers'
Requires-Dist: gputils ; extra == 'transformers'
Requires-Dist: transformers <4.41 ; extra == 'transformers'
Requires-Dist: datasets <2.19 ; extra == 'transformers'
Requires-Dist: dvc ; extra == 'transformers'
Requires-Dist: scikit-learn ; extra == 'transformers'
Requires-Dist: seqeval ; extra == 'transformers'
Requires-Dist: einops ; extra == 'transformers'
Requires-Dist: evaluate >=0.4.1 ; extra == 'transformers'
Requires-Dist: accelerate >=0.20.3 ; extra == 'transformers'
Requires-Dist: safetensors >=0.4.1 ; extra == 'transformers'
Requires-Dist: compressed-tensors-nightly ; extra == 'transformers'
Provides-Extra: ultralytics
Requires-Dist: ultralytics ==8.0.124 ; extra == 'ultralytics'
Requires-Dist: torch >=1.7.0 ; extra == 'ultralytics'
Provides-Extra: yolov5
Requires-Dist: torch >=1.7.0 ; extra == 'yolov5'
Requires-Dist: gputils ; extra == 'yolov5'
Requires-Dist: torchvision <0.17,>=0.3.0 ; extra == 'yolov5'
Requires-Dist: opencv-python <=4.6.0.66 ; extra == 'yolov5'
Requires-Dist: nm-yolov5-nightly <=1.8.0 ; extra == 'yolov5'
